Metadata-Version: 2.1
Name: discord-api-info
Version: 2.5
Summary: Library to retrieve the latest chrome user agent, version and latest discord client build number.
